[
 {
  "_id": "f8f61c58-1309-4bb5-96a2-966db2f8e270",
  "locationId": "YTi6qs4zhiW6d4a75A9f",
  "name": "Newport News Lead Notification",
  "status": "draft",
  "originId": "0435ec25-fba1-42af-aebf-14ff086b5af8",
  "permission": 380,
  "type": "workflow",
  "updatedBy": "snapshot",
  "createdAt": "2026-07-18T20:05:08.221Z",
  "updatedAt": "2026-07-18T20:05:22.670Z",
  "deleted": false,
  "dataVersion": 7,
  "parentId": "e2de4d34-1c75-46d7-89aa-b5df6e6394db",
  "permissionMeta": {
   "canRead": true,
   "canWrite": true
  },
  "id": "f8f61c58-1309-4bb5-96a2-966db2f8e270",
  "_folderPath": "01 - Lead Capture & Nurture"
 },
 {
  "_id": "f4e36c5c-bed6-4eea-a12b-143f19333bef",
  "locationId": "YTi6qs4zhiW6d4a75A9f",
  "name": "Newport News Non-Booked Recovery",
  "status": "draft",
  "originId": "a1898018-5aff-412b-a0af-720400c76877",
  "permission": 380,
  "type": "workflow",
  "updatedBy": "snapshot",
  "createdAt": "2026-07-18T20:05:08.621Z",
  "updatedAt": "2026-07-18T20:05:23.037Z",
  "deleted": false,
  "dataVersion": 7,
  "parentId": "e2de4d34-1c75-46d7-89aa-b5df6e6394db",
  "permissionMeta": {
   "canRead": true,
   "canWrite": true
  },
  "id": "f4e36c5c-bed6-4eea-a12b-143f19333bef",
  "_folderPath": "01 - Lead Capture & Nurture"
 },
 {
  "_id": "48fd4ffc-f067-4da1-8777-9065c4ad48a6",
  "locationId": "YTi6qs4zhiW6d4a75A9f",
  "name": "Richmond Lead Notification",
  "status": "draft",
  "originId": "03f8f885-f240-4f94-9074-6e76c20cc23e",
  "permission": 380,
  "type": "workflow",
  "updatedBy": "snapshot",
  "createdAt": "2026-07-18T20:05:10.155Z",
  "updatedAt": "2026-07-18T20:05:22.615Z",
  "deleted": false,
  "dataVersion": 7,
  "parentId": "ef7551a3-e52a-4fde-bd29-5754d63f164f",
  "permissionMeta": {
   "canRead": true,
   "canWrite": true
  },
  "id": "48fd4ffc-f067-4da1-8777-9065c4ad48a6",
  "_folderPath": "01 - Lead Capture & Nurture"
 },
 {
  "_id": "d9ac1ca5-8372-4dfc-bdf5-2a2b6a8cab40",
  "locationId": "YTi6qs4zhiW6d4a75A9f",
  "name": "Richmond Non-Booked Recovery",
  "status": "draft",
  "originId": "979b6f41-2f9e-4220-be77-4e3f1566cd2b",
  "permission": 380,
  "type": "workflow",
  "updatedBy": "snapshot",
  "createdAt": "2026-07-18T20:05:10.704Z",
  "updatedAt": "2026-07-18T20:05:23.645Z",
  "deleted": false,
  "dataVersion": 7,
  "parentId": "ef7551a3-e52a-4fde-bd29-5754d63f164f",
  "permissionMeta": {
   "canRead": true,
   "canWrite": true
  },
  "id": "d9ac1ca5-8372-4dfc-bdf5-2a2b6a8cab40",
  "_folderPath": "01 - Lead Capture & Nurture"
 },
 {
  "_id": "ba24747e-5ef4-494d-ba65-91db0de5ac29",
  "locationId": "YTi6qs4zhiW6d4a75A9f",
  "name": "Virginia Lead Notification",
  "status": "draft",
  "originId": "808645ab-555e-45ed-be12-ff83815d7aab",
  "permission": 380,
  "type": "workflow",
  "updatedBy": "snapshot",
  "createdAt": "2026-07-18T20:05:12.248Z",
  "updatedAt": "2026-07-18T20:05:23.747Z",
  "deleted": false,
  "dataVersion": 7,
  "parentId": "9f1bc354-2fc2-47f9-95bc-9cff44ef1b47",
  "permissionMeta": {
   "canRead": true,
   "canWrite": true
  },
  "id": "ba24747e-5ef4-494d-ba65-91db0de5ac29",
  "_folderPath": "01 - Lead Capture & Nurture"
 },
 {
  "_id": "1c3d0523-d549-47cd-a4c2-83f37883e062",
  "locationId": "YTi6qs4zhiW6d4a75A9f",
  "name": "Virginia Non-Booked Recovery",
  "status": "draft",
  "originId": "e43548bb-b6f7-4109-905b-1e03598fe708",
  "permission": 380,
  "type": "workflow",
  "updatedBy": "snapshot",
  "createdAt": "2026-07-18T20:05:12.456Z",
  "updatedAt": "2026-07-18T20:05:23.723Z",
  "deleted": false,
  "dataVersion": 7,
  "parentId": "9f1bc354-2fc2-47f9-95bc-9cff44ef1b47",
  "permissionMeta": {
   "canRead": true,
   "canWrite": true
  },
  "id": "1c3d0523-d549-47cd-a4c2-83f37883e062",
  "_folderPath": "01 - Lead Capture & Nurture"
 },
 {
  "_id": "5bb22f3f-9ee3-4309-8b5e-bfa6d02644c9",
  "locationId": "YTi6qs4zhiW6d4a75A9f",
  "name": "Newport News Booking Confirmation",
  "status": "draft",
  "originId": "80df6346-3534-4f53-86d1-30a6a8aed912",
  "permission": 380,
  "type": "workflow",
  "updatedBy": "snapshot",
  "createdAt": "2026-07-18T20:05:07.845Z",
  "updatedAt": "2026-07-18T20:05:22.589Z",
  "deleted": false,
  "dataVersion": 7,
  "parentId": "8263b384-4a7c-40f1-b012-2fa8ecaf2200",
  "permissionMeta": {
   "canRead": true,
   "canWrite": true
  },
  "id": "5bb22f3f-9ee3-4309-8b5e-bfa6d02644c9",
  "_folderPath": "02 - Booking & Confirmation"
 },
 {
  "_id": "38e96d86-3792-40f9-b950-a289bb42d2e6",
  "locationId": "YTi6qs4zhiW6d4a75A9f",
  "name": "Richmond Booking Confirmation",
  "status": "draft",
  "originId": "18c985b5-99c4-4500-b059-96a16ebb5ef8",
  "permission": 380,
  "type": "workflow",
  "updatedBy": "snapshot",
  "createdAt": "2026-07-18T20:05:09.302Z",
  "updatedAt": "2026-07-18T20:05:22.587Z",
  "deleted": false,
  "dataVersion": 7,
  "parentId": "b2e59204-95f5-4de2-b54e-2fd3d478ace0",
  "permissionMeta": {
   "canRead": true,
   "canWrite": true
  },
  "id": "38e96d86-3792-40f9-b950-a289bb42d2e6",
  "_folderPath": "02 - Booking & Confirmation"
 },
 {
  "_id": "21680c0e-e8c2-469a-95a1-06ff14f2df12",
  "locationId": "YTi6qs4zhiW6d4a75A9f",
  "name": "Virginia Booking Confirmation",
  "status": "draft",
  "originId": "fdb5d9b5-f898-4fd0-b8bd-6cf3bfc2c2e5",
  "permission": 380,
  "type": "workflow",
  "updatedBy": "snapshot",
  "createdAt": "2026-07-18T20:05:12.042Z",
  "updatedAt": "2026-07-18T20:05:23.681Z",
  "deleted": false,
  "dataVersion": 7,
  "parentId": "76d206a5-88da-468e-9793-8c2463973cc6",
  "permissionMeta": {
   "canRead": true,
   "canWrite": true
  },
  "id": "21680c0e-e8c2-469a-95a1-06ff14f2df12",
  "_folderPath": "02 - Booking & Confirmation"
 },
 {
  "_id": "7e6186d7-7c30-48eb-aa7d-947ce6b93f15",
  "locationId": "YTi6qs4zhiW6d4a75A9f",
  "name": "Medical Intake Reminder Chase",
  "status": "draft",
  "originId": "3cdfb950-ad1f-40f4-8fe6-a8f967c60ecf",
  "permission": 380,
  "type": "workflow",
  "updatedBy": "snapshot",
  "createdAt": "2026-07-18T20:05:07.647Z",
  "updatedAt": "2026-07-18T20:05:22.592Z",
  "deleted": false,
  "dataVersion": 7,
  "parentId": "15de2e06-8072-43e7-b28e-da80ea1d8507",
  "permissionMeta": {
   "canRead": true,
   "canWrite": true
  },
  "id": "7e6186d7-7c30-48eb-aa7d-947ce6b93f15",
  "_folderPath": "03 - Intake"
 },
 {
  "_id": "a9c5e9cd-c6da-494c-844f-be6b504829b9",
  "locationId": "YTi6qs4zhiW6d4a75A9f",
  "name": "Medical Intake Reminder Chase",
  "status": "draft",
  "originId": "0801e878-c279-4a67-b25b-ce3483956a94",
  "permission": 380,
  "type": "workflow",
  "updatedBy": "snapshot",
  "createdAt": "2026-07-18T20:05:07.433Z",
  "updatedAt": "2026-07-18T20:05:22.575Z",
  "deleted": false,
  "dataVersion": 7,
  "parentId": "89df6cda-4c73-4c1b-b785-858b7f928748",
  "permissionMeta": {
   "canRead": true,
   "canWrite": true
  },
  "id": "a9c5e9cd-c6da-494c-844f-be6b504829b9",
  "_folderPath": "03 - Intake"
 },
 {
  "_id": "ee76fcea-4156-4f6b-9daa-cde95eefd570",
  "locationId": "YTi6qs4zhiW6d4a75A9f",
  "name": "Virginia Beach - Medical Intake Reminder Chase",
  "status": "draft",
  "originId": "238bc304-954d-45ce-be54-2a7e1c2b6008",
  "permission": 380,
  "type": "workflow",
  "updatedBy": "snapshot",
  "createdAt": "2026-07-18T20:05:11.404Z",
  "updatedAt": "2026-07-18T20:05:23.902Z",
  "deleted": false,
  "dataVersion": 7,
  "parentId": "0b6a0b3b-c12d-43ce-bc6e-da1d492a3009",
  "permissionMeta": {
   "canRead": true,
   "canWrite": true
  },
  "id": "ee76fcea-4156-4f6b-9daa-cde95eefd570",
  "_folderPath": "03 - Intake"
 },
 {
  "_id": "d3cb36d6-3359-42a6-b812-e66bbba525a6",
  "locationId": "YTi6qs4zhiW6d4a75A9f",
  "name": "Newport News Cancellation Recovery",
  "status": "draft",
  "originId": "6de72a41-6d70-42f2-8e6c-9b197e0e8bfd",
  "permission": 380,
  "type": "workflow",
  "updatedBy": "snapshot",
  "createdAt": "2026-07-18T20:05:08.033Z",
  "updatedAt": "2026-07-18T20:05:22.623Z",
  "deleted": false,
  "dataVersion": 7,
  "parentId": "3463d980-8fb8-4e24-b13f-d7b7e5a25900",
  "permissionMeta": {
   "canRead": true,
   "canWrite": true
  },
  "id": "d3cb36d6-3359-42a6-b812-e66bbba525a6",
  "_folderPath": "04 - Reschedule / Cancel / No-Show"
 },
 {
  "_id": "6f07bebb-fef2-4491-abb5-ae9cb8135ba0",
  "locationId": "YTi6qs4zhiW6d4a75A9f",
  "name": "Newport News No-Show Recovery",
  "status": "draft",
  "originId": "c5bcac93-a068-400a-b180-5c69002a0d3a",
  "permission": 380,
  "type": "workflow",
  "updatedBy": "snapshot",
  "createdAt": "2026-07-18T20:05:08.427Z",
  "updatedAt": "2026-07-18T20:05:22.640Z",
  "deleted": false,
  "dataVersion": 7,
  "parentId": "3463d980-8fb8-4e24-b13f-d7b7e5a25900",
  "permissionMeta": {
   "canRead": true,
   "canWrite": true
  },
  "id": "6f07bebb-fef2-4491-abb5-ae9cb8135ba0",
  "_folderPath": "04 - Reschedule / Cancel / No-Show"
 },
 {
  "_id": "69a61b66-a305-4f4d-91f8-f1ba49b288e3",
  "locationId": "YTi6qs4zhiW6d4a75A9f",
  "name": "Richmond Cancellation Recovery",
  "status": "draft",
  "originId": "417fd1ca-d761-4493-9dbc-3498bfccb0fa",
  "permission": 380,
  "type": "workflow",
  "updatedBy": "snapshot",
  "createdAt": "2026-07-18T20:05:09.970Z",
  "updatedAt": "2026-07-18T20:05:22.578Z",
  "deleted": false,
  "dataVersion": 7,
  "parentId": "d0931241-ae7e-4168-ad98-3319feb87fb6",
  "permissionMeta": {
   "canRead": true,
   "canWrite": true
  },
  "id": "69a61b66-a305-4f4d-91f8-f1ba49b288e3",
  "_folderPath": "04 - Reschedule / Cancel / No-Show"
 },
 {
  "_id": "28d65c1e-ab76-4165-b86f-14da853756a5",
  "locationId": "YTi6qs4zhiW6d4a75A9f",
  "name": "Richmond No-Show Recovery",
  "status": "draft",
  "originId": "5e8fad4e-d41a-4bef-a3d4-7dd80d4f052b",
  "permission": 380,
  "type": "workflow",
  "updatedBy": "snapshot",
  "createdAt": "2026-07-18T20:05:10.491Z",
  "updatedAt": "2026-07-18T20:05:23.653Z",
  "deleted": false,
  "dataVersion": 7,
  "parentId": "d0931241-ae7e-4168-ad98-3319feb87fb6",
  "permissionMeta": {
   "canRead": true,
   "canWrite": true
  },
  "id": "28d65c1e-ab76-4165-b86f-14da853756a5",
  "_folderPath": "04 - Reschedule / Cancel / No-Show"
 },
 {
  "_id": "065bbd34-04d2-4aed-a6c4-e3b5b0451480",
  "locationId": "YTi6qs4zhiW6d4a75A9f",
  "name": "Virginia Beach Cancellation Recovery",
  "status": "draft",
  "originId": "034851d6-c81e-4177-a521-62eeab85dc98",
  "permission": 380,
  "type": "workflow",
  "updatedBy": "snapshot",
  "createdAt": "2026-07-18T20:05:11.607Z",
  "updatedAt": "2026-07-18T20:05:23.673Z",
  "deleted": false,
  "dataVersion": 7,
  "parentId": "11e9e5c9-b93c-4e95-a271-09c1196f4f73",
  "permissionMeta": {
   "canRead": true,
   "canWrite": true
  },
  "id": "065bbd34-04d2-4aed-a6c4-e3b5b0451480",
  "_folderPath": "04 - Reschedule / Cancel / No-Show"
 },
 {
  "_id": "2bd925bc-4203-405e-b763-bbb531f7778b",
  "locationId": "YTi6qs4zhiW6d4a75A9f",
  "name": "Virginia Beach No-Show Recovery",
  "status": "draft",
  "originId": "d0d55f71-04dd-402f-a06e-b9a09b7cb888",
  "permission": 380,
  "type": "workflow",
  "updatedBy": "snapshot",
  "createdAt": "2026-07-18T20:05:11.816Z",
  "updatedAt": "2026-07-18T20:05:23.672Z",
  "deleted": false,
  "dataVersion": 7,
  "parentId": "11e9e5c9-b93c-4e95-a271-09c1196f4f73",
  "permissionMeta": {
   "canRead": true,
   "canWrite": true
  },
  "id": "2bd925bc-4203-405e-b763-bbb531f7778b",
  "_folderPath": "04 - Reschedule / Cancel / No-Show"
 },
 {
  "_id": "bc78fb80-7a7c-4f29-a79e-2ce432afad30",
  "locationId": "YTi6qs4zhiW6d4a75A9f",
  "name": "5.1 — Newport News – PCC Disposition Router",
  "status": "draft",
  "originId": "56ca5b7e-24a2-4002-bad2-459460161dea",
  "permission": 380,
  "type": "workflow",
  "meta": {},
  "updatedBy": "snapshot",
  "createdAt": "2026-07-18T20:04:58.587Z",
  "updatedAt": "2026-07-18T20:05:20.069Z",
  "deleted": false,
  "dataVersion": 7,
  "parentId": "7cfaadd6-d59f-4e9f-b8d5-0a1efabd96d0",
  "permissionMeta": {
   "canRead": true,
   "canWrite": true
  },
  "id": "bc78fb80-7a7c-4f29-a79e-2ce432afad30",
  "_folderPath": "05 - Sales & Disposition"
 },
 {
  "_id": "f09dc586-f25f-419a-b0c7-f7c013712fe3",
  "locationId": "YTi6qs4zhiW6d4a75A9f",
  "name": "5.1 — Richmond – PCC Disposition Router",
  "status": "draft",
  "originId": "6b662a8a-fe58-40d3-ae3a-d88b7978415f",
  "permission": 380,
  "type": "workflow",
  "meta": {},
  "updatedBy": "snapshot",
  "createdAt": "2026-07-18T20:04:58.800Z",
  "updatedAt": "2026-07-18T20:05:21.286Z",
  "deleted": false,
  "dataVersion": 7,
  "parentId": "767e289f-f1e4-4a2a-87a4-960700f242a8",
  "permissionMeta": {
   "canRead": true,
   "canWrite": true
  },
  "id": "f09dc586-f25f-419a-b0c7-f7c013712fe3",
  "_folderPath": "05 - Sales & Disposition"
 },
 {
  "_id": "3f95f7b4-5488-4114-9807-e77c1345d45c",
  "locationId": "YTi6qs4zhiW6d4a75A9f",
  "name": "5.1 — Virginia Beach – PCC Disposition Router",
  "status": "draft",
  "originId": "9b7f7f9a-2644-4109-a3ac-41931f3f05a3",
  "permission": 380,
  "type": "workflow",
  "meta": {},
  "updatedBy": "snapshot",
  "createdAt": "2026-07-18T20:04:59.007Z",
  "updatedAt": "2026-07-18T20:05:21.417Z",
  "deleted": false,
  "dataVersion": 7,
  "parentId": "96edf89b-5792-4552-a476-6cc62ee98b41",
  "permissionMeta": {
   "canRead": true,
   "canWrite": true
  },
  "id": "3f95f7b4-5488-4114-9807-e77c1345d45c",
  "_folderPath": "05 - Sales & Disposition"
 },
 {
  "_id": "23b90983-14d8-47d8-8f8f-6a65032f9de5",
  "locationId": "YTi6qs4zhiW6d4a75A9f",
  "name": "5.2 — Newport News – Won & Onboarding",
  "status": "draft",
  "originId": "9a502d0e-1ad7-4b14-b941-f8fc76d4f8f1",
  "permission": 380,
  "type": "workflow",
  "updatedBy": "snapshot",
  "createdAt": "2026-07-18T20:04:59.195Z",
  "updatedAt": "2026-07-18T20:05:21.353Z",
  "deleted": false,
  "dataVersion": 7,
  "parentId": "7cfaadd6-d59f-4e9f-b8d5-0a1efabd96d0",
  "permissionMeta": {
   "canRead": true,
   "canWrite": true
  },
  "id": "23b90983-14d8-47d8-8f8f-6a65032f9de5",
  "_folderPath": "05 - Sales & Disposition"
 },
 {
  "_id": "cfe54298-e03e-4c59-a1c8-eace77720fa4",
  "locationId": "YTi6qs4zhiW6d4a75A9f",
  "name": "5.2 — Richmond – Won & Onboarding",
  "status": "draft",
  "originId": "1cd0026f-7e07-41aa-9427-2a9e72d75160",
  "permission": 380,
  "type": "workflow",
  "updatedBy": "snapshot",
  "createdAt": "2026-07-18T20:04:59.406Z",
  "updatedAt": "2026-07-18T20:05:21.362Z",
  "deleted": false,
  "dataVersion": 7,
  "parentId": "767e289f-f1e4-4a2a-87a4-960700f242a8",
  "permissionMeta": {
   "canRead": true,
   "canWrite": true
  },
  "id": "cfe54298-e03e-4c59-a1c8-eace77720fa4",
  "_folderPath": "05 - Sales & Disposition"
 },
 {
  "_id": "8f61ccdf-d4c4-4b49-9aa7-a56bf3baded7",
  "locationId": "YTi6qs4zhiW6d4a75A9f",
  "name": "5.2 — Virginia Beach – Won & Onboarding",
  "status": "draft",
  "originId": "d4bec717-d3e1-4f6d-94ed-d961ead8468e",
  "permission": 380,
  "type": "workflow",
  "updatedBy": "snapshot",
  "createdAt": "2026-07-18T20:04:59.617Z",
  "updatedAt": "2026-07-18T20:05:21.423Z",
  "deleted": false,
  "dataVersion": 7,
  "parentId": "96edf89b-5792-4552-a476-6cc62ee98b41",
  "permissionMeta": {
   "canRead": true,
   "canWrite": true
  },
  "id": "8f61ccdf-d4c4-4b49-9aa7-a56bf3baded7",
  "_folderPath": "05 - Sales & Disposition"
 },
 {
  "_id": "61d931ac-efea-43a7-97ee-074ca16df585",
  "locationId": "YTi6qs4zhiW6d4a75A9f",
  "name": "5.3 — Newport News – Feedback Survey",
  "status": "draft",
  "originId": "8e52e5b4-f070-4904-81bc-618d04d65b45",
  "permission": 380,
  "type": "workflow",
  "updatedBy": "snapshot",
  "createdAt": "2026-07-18T20:04:59.845Z",
  "updatedAt": "2026-07-18T20:05:21.418Z",
  "deleted": false,
  "dataVersion": 7,
  "parentId": "7cfaadd6-d59f-4e9f-b8d5-0a1efabd96d0",
  "permissionMeta": {
   "canRead": true,
   "canWrite": true
  },
  "id": "61d931ac-efea-43a7-97ee-074ca16df585",
  "_folderPath": "05 - Sales & Disposition"
 },
 {
  "_id": "068fb10f-5b07-4807-932e-3646e7300e52",
  "locationId": "YTi6qs4zhiW6d4a75A9f",
  "name": "5.3 — Richmond – Feedback Survey",
  "status": "draft",
  "originId": "14d4e1ab-f02a-4277-b136-7d9310ec7a67",
  "permission": 380,
  "type": "workflow",
  "updatedBy": "snapshot",
  "createdAt": "2026-07-18T20:05:00.075Z",
  "updatedAt": "2026-07-18T20:05:21.391Z",
  "deleted": false,
  "dataVersion": 7,
  "parentId": "767e289f-f1e4-4a2a-87a4-960700f242a8",
  "permissionMeta": {
   "canRead": true,
   "canWrite": true
  },
  "id": "068fb10f-5b07-4807-932e-3646e7300e52",
  "_folderPath": "05 - Sales & Disposition"
 },
 {
  "_id": "1300cc56-ffb2-4118-bbf9-5faf60af4b60",
  "locationId": "YTi6qs4zhiW6d4a75A9f",
  "name": "5.3 — Virginia Beach – Feedback Survey",
  "status": "draft",
  "originId": "6016d658-8acc-42e3-a402-efb6230c3f6c",
  "permission": 380,
  "type": "workflow",
  "updatedBy": "snapshot",
  "createdAt": "2026-07-18T20:05:00.304Z",
  "updatedAt": "2026-07-18T20:05:21.409Z",
  "deleted": false,
  "dataVersion": 7,
  "parentId": "96edf89b-5792-4552-a476-6cc62ee98b41",
  "permissionMeta": {
   "canRead": true,
   "canWrite": true
  },
  "id": "1300cc56-ffb2-4118-bbf9-5faf60af4b60",
  "_folderPath": "05 - Sales & Disposition"
 },
 {
  "_id": "65022c6c-2d8f-43f9-9676-aa5c9b520cc6",
  "locationId": "YTi6qs4zhiW6d4a75A9f",
  "name": "5.4a–e — Newport News - A&D Nurture - All Objections",
  "status": "draft",
  "originId": "3e4c99d6-f05d-496c-b1d5-e0d842600ffc",
  "permission": 380,
  "type": "workflow",
  "updatedBy": "snapshot",
  "createdAt": "2026-07-18T20:05:00.535Z",
  "updatedAt": "2026-07-18T20:05:21.403Z",
  "deleted": false,
  "dataVersion": 7,
  "parentId": "7cfaadd6-d59f-4e9f-b8d5-0a1efabd96d0",
  "permissionMeta": {
   "canRead": true,
   "canWrite": true
  },
  "id": "65022c6c-2d8f-43f9-9676-aa5c9b520cc6",
  "_folderPath": "05 - Sales & Disposition"
 },
 {
  "_id": "c1b63f51-7a4d-4219-ae37-c09a785c2ac6",
  "locationId": "YTi6qs4zhiW6d4a75A9f",
  "name": "5.4a–e — Richmond - A&D Nurture - All Objections",
  "status": "draft",
  "originId": "3e09a81d-93c4-4b28-a280-779124f7d178",
  "permission": 380,
  "type": "workflow",
  "updatedBy": "snapshot",
  "createdAt": "2026-07-18T20:05:00.735Z",
  "updatedAt": "2026-07-18T20:05:21.388Z",
  "deleted": false,
  "dataVersion": 7,
  "parentId": "767e289f-f1e4-4a2a-87a4-960700f242a8",
  "permissionMeta": {
   "canRead": true,
   "canWrite": true
  },
  "id": "c1b63f51-7a4d-4219-ae37-c09a785c2ac6",
  "_folderPath": "05 - Sales & Disposition"
 },
 {
  "_id": "202fb467-32e0-4374-931d-b0842c119bfb",
  "locationId": "YTi6qs4zhiW6d4a75A9f",
  "name": "5.4a–e — Virginia Beach - A&D Nurture - All Objections",
  "status": "draft",
  "originId": "8bfcf6c2-e57c-4af9-a280-75233175c18b",
  "permission": 380,
  "type": "workflow",
  "updatedBy": "snapshot",
  "createdAt": "2026-07-18T20:05:00.948Z",
  "updatedAt": "2026-07-18T20:05:21.394Z",
  "deleted": false,
  "dataVersion": 7,
  "parentId": "96edf89b-5792-4552-a476-6cc62ee98b41",
  "permissionMeta": {
   "canRead": true,
   "canWrite": true
  },
  "id": "202fb467-32e0-4374-931d-b0842c119bfb",
  "_folderPath": "05 - Sales & Disposition"
 },
 {
  "_id": "b86f1720-6bf7-48de-a547-7c586b93f0e5",
  "locationId": "YTi6qs4zhiW6d4a75A9f",
  "name": "5.5 — Newport News – Long-Term Nurture",
  "status": "draft",
  "originId": "5a6f3c32-ce50-4190-829d-eca6049adf9d",
  "permission": 380,
  "type": "workflow",
  "updatedBy": "snapshot",
  "createdAt": "2026-07-18T20:05:01.168Z",
  "updatedAt": "2026-07-18T20:05:21.388Z",
  "deleted": false,
  "dataVersion": 7,
  "parentId": "7cfaadd6-d59f-4e9f-b8d5-0a1efabd96d0",
  "permissionMeta": {
   "canRead": true,
   "canWrite": true
  },
  "id": "b86f1720-6bf7-48de-a547-7c586b93f0e5",
  "_folderPath": "05 - Sales & Disposition"
 },
 {
  "_id": "55761857-c11a-4cea-9bfd-31d75e93df39",
  "locationId": "YTi6qs4zhiW6d4a75A9f",
  "name": "5.5 — Richmond – Long-Term Nurture",
  "status": "draft",
  "originId": "d223ba43-7f11-42d2-a5a0-87d48e768530",
  "permission": 380,
  "type": "workflow",
  "updatedBy": "snapshot",
  "createdAt": "2026-07-18T20:05:01.369Z",
  "updatedAt": "2026-07-18T20:05:21.418Z",
  "deleted": false,
  "dataVersion": 7,
  "parentId": "767e289f-f1e4-4a2a-87a4-960700f242a8",
  "permissionMeta": {
   "canRead": true,
   "canWrite": true
  },
  "id": "55761857-c11a-4cea-9bfd-31d75e93df39",
  "_folderPath": "05 - Sales & Disposition"
 },
 {
  "_id": "81b52161-940a-4731-84a5-a84e474b3a3f",
  "locationId": "YTi6qs4zhiW6d4a75A9f",
  "name": "5.5 — Virginia Beach – Long-Term Nurture",
  "status": "draft",
  "originId": "c8c3ebfe-a8ce-4d65-9283-1593d677aaf5",
  "permission": 380,
  "type": "workflow",
  "updatedBy": "snapshot",
  "createdAt": "2026-07-18T20:05:01.591Z",
  "updatedAt": "2026-07-18T20:05:21.385Z",
  "deleted": false,
  "dataVersion": 7,
  "parentId": "96edf89b-5792-4552-a476-6cc62ee98b41",
  "permissionMeta": {
   "canRead": true,
   "canWrite": true
  },
  "id": "81b52161-940a-4731-84a5-a84e474b3a3f",
  "_folderPath": "05 - Sales & Disposition"
 },
 {
  "_id": "ab197a37-525b-49ca-9b10-4341ccef70c0",
  "locationId": "YTi6qs4zhiW6d4a75A9f",
  "name": "5.6 — Newport News – Term Extension (+3 Months)",
  "status": "draft",
  "originId": "a33ba088-0dc0-41ae-949d-844531f73250",
  "permission": 380,
  "type": "workflow",
  "updatedBy": "snapshot",
  "createdAt": "2026-07-18T20:05:01.914Z",
  "updatedAt": "2026-07-18T20:05:21.726Z",
  "deleted": false,
  "dataVersion": 7,
  "parentId": "7cfaadd6-d59f-4e9f-b8d5-0a1efabd96d0",
  "permissionMeta": {
   "canRead": true,
   "canWrite": true
  },
  "id": "ab197a37-525b-49ca-9b10-4341ccef70c0",
  "_folderPath": "05 - Sales & Disposition"
 },
 {
  "_id": "50bb7b70-1b1f-4607-b12b-08ae42241314",
  "locationId": "YTi6qs4zhiW6d4a75A9f",
  "name": "5.6 — Richmond – Term Extension (+3 Months)",
  "status": "draft",
  "originId": "6be638f3-8ffd-40cc-a66a-ac3eb423ae65",
  "permission": 380,
  "type": "workflow",
  "updatedBy": "snapshot",
  "createdAt": "2026-07-18T20:05:02.128Z",
  "updatedAt": "2026-07-18T20:05:21.424Z",
  "deleted": false,
  "dataVersion": 7,
  "parentId": "767e289f-f1e4-4a2a-87a4-960700f242a8",
  "permissionMeta": {
   "canRead": true,
   "canWrite": true
  },
  "id": "50bb7b70-1b1f-4607-b12b-08ae42241314",
  "_folderPath": "05 - Sales & Disposition"
 },
 {
  "_id": "9744e1fe-3b11-47da-886c-46c8e1c5c9f2",
  "locationId": "YTi6qs4zhiW6d4a75A9f",
  "name": "5.6 — Virginia Beach – Term Extension (+3 Months)",
  "status": "draft",
  "originId": "9a81bd32-2803-4779-b65d-cd5897f2dd72",
  "permission": 380,
  "type": "workflow",
  "updatedBy": "snapshot",
  "createdAt": "2026-07-18T20:05:02.343Z",
  "updatedAt": "2026-07-18T20:05:21.731Z",
  "deleted": false,
  "dataVersion": 7,
  "parentId": "96edf89b-5792-4552-a476-6cc62ee98b41",
  "permissionMeta": {
   "canRead": true,
   "canWrite": true
  },
  "id": "9744e1fe-3b11-47da-886c-46c8e1c5c9f2",
  "_folderPath": "05 - Sales & Disposition"
 },
 {
  "_id": "c4493a40-4b43-4bf2-8d66-56d832484973",
  "locationId": "YTi6qs4zhiW6d4a75A9f",
  "name": "6.1 Newport News Lapsed Win-Back",
  "status": "draft",
  "originId": "1e0da3a7-eaa2-4829-b5b4-af50c2b79a72",
  "permission": 380,
  "type": "workflow",
  "updatedBy": "snapshot",
  "createdAt": "2026-07-18T20:05:02.552Z",
  "updatedAt": "2026-07-18T20:05:21.378Z",
  "deleted": false,
  "dataVersion": 7,
  "parentId": "aed9b3b5-38ed-4b2d-9734-da447a620ed1",
  "permissionMeta": {
   "canRead": true,
   "canWrite": true
  },
  "id": "c4493a40-4b43-4bf2-8d66-56d832484973",
  "_folderPath": "06 - Retention & Renewals"
 },
 {
  "_id": "5a3c17e2-276d-4df5-8a50-d37c9fc077a9",
  "locationId": "YTi6qs4zhiW6d4a75A9f",
  "name": "6.1 Richmond Lapsed Win-Back",
  "status": "draft",
  "originId": "7deaeb4e-180c-47f9-8066-fd96227cb24f",
  "permission": 380,
  "type": "workflow",
  "updatedBy": "snapshot",
  "createdAt": "2026-07-18T20:05:02.768Z",
  "updatedAt": "2026-07-18T20:05:21.385Z",
  "deleted": false,
  "dataVersion": 7,
  "parentId": "1f9a94d6-57d9-4d8f-a2c1-9eab2d15ab76",
  "permissionMeta": {
   "canRead": true,
   "canWrite": true
  },
  "id": "5a3c17e2-276d-4df5-8a50-d37c9fc077a9",
  "_folderPath": "06 - Retention & Renewals"
 },
 {
  "_id": "0fd1af8a-1301-4e6e-aeeb-1f86c96375b9",
  "locationId": "YTi6qs4zhiW6d4a75A9f",
  "name": "6.1 Virginia Beach Lapsed Win-Back",
  "status": "draft",
  "originId": "7ebeaf66-58dc-409d-9260-8e17e6adbb69",
  "permission": 380,
  "type": "workflow",
  "updatedBy": "snapshot",
  "createdAt": "2026-07-18T20:05:02.969Z",
  "updatedAt": "2026-07-18T20:05:21.409Z",
  "deleted": false,
  "dataVersion": 7,
  "parentId": "a0f037a0-e653-4f99-8e22-b5ea313be0e1",
  "permissionMeta": {
   "canRead": true,
   "canWrite": true
  },
  "id": "0fd1af8a-1301-4e6e-aeeb-1f86c96375b9",
  "_folderPath": "06 - Retention & Renewals"
 },
 {
  "_id": "894b9547-a7a7-437f-b83e-c122c0b98f4f",
  "locationId": "YTi6qs4zhiW6d4a75A9f",
  "name": "6.2 Newport News Renewal Reminder",
  "status": "draft",
  "originId": "4a7a05f0-9e24-43a9-9330-dbb0ff7f153d",
  "permission": 380,
  "type": "workflow",
  "updatedBy": "snapshot",
  "createdAt": "2026-07-18T20:05:03.185Z",
  "updatedAt": "2026-07-18T20:05:21.467Z",
  "deleted": false,
  "dataVersion": 7,
  "parentId": "aed9b3b5-38ed-4b2d-9734-da447a620ed1",
  "permissionMeta": {
   "canRead": true,
   "canWrite": true
  },
  "id": "894b9547-a7a7-437f-b83e-c122c0b98f4f",
  "_folderPath": "06 - Retention & Renewals"
 },
 {
  "_id": "f4f724b7-4435-45cd-b07b-dd1f91b18425",
  "locationId": "YTi6qs4zhiW6d4a75A9f",
  "name": "6.2 Richmond Renewal Reminder",
  "status": "draft",
  "originId": "9748cf8c-82bf-431c-9c5c-b273a831743b",
  "permission": 380,
  "type": "workflow",
  "updatedBy": "snapshot",
  "createdAt": "2026-07-18T20:05:03.434Z",
  "updatedAt": "2026-07-18T20:05:21.378Z",
  "deleted": false,
  "dataVersion": 7,
  "parentId": "1f9a94d6-57d9-4d8f-a2c1-9eab2d15ab76",
  "permissionMeta": {
   "canRead": true,
   "canWrite": true
  },
  "id": "f4f724b7-4435-45cd-b07b-dd1f91b18425",
  "_folderPath": "06 - Retention & Renewals"
 },
 {
  "_id": "107cc989-37fe-4729-a5d1-991d3abf3a51",
  "locationId": "YTi6qs4zhiW6d4a75A9f",
  "name": "6.2 Virginia Beach Renewal Reminder",
  "status": "draft",
  "originId": "2555d07f-dc17-4283-899a-6a6a9e4fa56c",
  "permission": 380,
  "type": "workflow",
  "updatedBy": "snapshot",
  "createdAt": "2026-07-18T20:05:03.638Z",
  "updatedAt": "2026-07-18T20:05:21.709Z",
  "deleted": false,
  "dataVersion": 7,
  "parentId": "a0f037a0-e653-4f99-8e22-b5ea313be0e1",
  "permissionMeta": {
   "canRead": true,
   "canWrite": true
  },
  "id": "107cc989-37fe-4729-a5d1-991d3abf3a51",
  "_folderPath": "06 - Retention & Renewals"
 },
 {
  "_id": "dc116bdb-6cd1-49cb-8d46-38c992ff42cc",
  "locationId": "YTi6qs4zhiW6d4a75A9f",
  "name": "6.3 Newport News Retention Touch",
  "status": "draft",
  "originId": "1957b993-9841-42aa-9858-fb6d43c70ff4",
  "permission": 380,
  "type": "workflow",
  "meta": {},
  "updatedBy": "snapshot",
  "createdAt": "2026-07-18T20:05:03.911Z",
  "updatedAt": "2026-07-18T20:05:21.418Z",
  "deleted": false,
  "dataVersion": 7,
  "parentId": "aed9b3b5-38ed-4b2d-9734-da447a620ed1",
  "permissionMeta": {
   "canRead": true,
   "canWrite": true
  },
  "id": "dc116bdb-6cd1-49cb-8d46-38c992ff42cc",
  "_folderPath": "06 - Retention & Renewals"
 },
 {
  "_id": "52c69682-7b1f-4e43-a3db-7c3cc4a5da10",
  "locationId": "YTi6qs4zhiW6d4a75A9f",
  "name": "6.3 Richmond Retention Touch",
  "status": "draft",
  "originId": "ab6dd748-d1e7-4c24-b431-fd522a5cd0b2",
  "permission": 380,
  "type": "workflow",
  "meta": {},
  "updatedBy": "snapshot",
  "createdAt": "2026-07-18T20:05:04.111Z",
  "updatedAt": "2026-07-18T20:05:21.401Z",
  "deleted": false,
  "dataVersion": 7,
  "parentId": "1f9a94d6-57d9-4d8f-a2c1-9eab2d15ab76",
  "permissionMeta": {
   "canRead": true,
   "canWrite": true
  },
  "id": "52c69682-7b1f-4e43-a3db-7c3cc4a5da10",
  "_folderPath": "06 - Retention & Renewals"
 },
 {
  "_id": "ca60db7a-2070-46c2-88ad-7ad993867368",
  "locationId": "YTi6qs4zhiW6d4a75A9f",
  "name": "6.3 Virginia Beach Retention Touch",
  "status": "draft",
  "originId": "d2391c99-a18f-420c-bc33-eb8407a93282",
  "permission": 380,
  "type": "workflow",
  "meta": {},
  "updatedBy": "snapshot",
  "createdAt": "2026-07-18T20:05:04.307Z",
  "updatedAt": "2026-07-18T20:05:21.346Z",
  "deleted": false,
  "dataVersion": 7,
  "parentId": "a0f037a0-e653-4f99-8e22-b5ea313be0e1",
  "permissionMeta": {
   "canRead": true,
   "canWrite": true
  },
  "id": "ca60db7a-2070-46c2-88ad-7ad993867368",
  "_folderPath": "06 - Retention & Renewals"
 },
 {
  "_id": "05272005-da06-4c83-8570-1db5f538538d",
  "locationId": "YTi6qs4zhiW6d4a75A9f",
  "name": "6.4 Newport News Term Extension",
  "status": "draft",
  "originId": "72bdb8fa-5393-4645-9416-6bef50b71374",
  "permission": 380,
  "type": "workflow",
  "updatedBy": "snapshot",
  "createdAt": "2026-07-18T20:05:04.506Z",
  "updatedAt": "2026-07-18T20:05:22.661Z",
  "deleted": false,
  "dataVersion": 7,
  "parentId": "aed9b3b5-38ed-4b2d-9734-da447a620ed1",
  "permissionMeta": {
   "canRead": true,
   "canWrite": true
  },
  "id": "05272005-da06-4c83-8570-1db5f538538d",
  "_folderPath": "06 - Retention & Renewals"
 },
 {
  "_id": "120134e1-606c-4d45-92b9-9544e13a9371",
  "locationId": "YTi6qs4zhiW6d4a75A9f",
  "name": "6.4 Richmond Term Extension",
  "status": "draft",
  "originId": "f16e9c17-402e-40bc-94e6-8537b64958b5",
  "permission": 380,
  "type": "workflow",
  "updatedBy": "snapshot",
  "createdAt": "2026-07-18T20:05:04.715Z",
  "updatedAt": "2026-07-18T20:05:22.544Z",
  "deleted": false,
  "dataVersion": 7,
  "parentId": "1f9a94d6-57d9-4d8f-a2c1-9eab2d15ab76",
  "permissionMeta": {
   "canRead": true,
   "canWrite": true
  },
  "id": "120134e1-606c-4d45-92b9-9544e13a9371",
  "_folderPath": "06 - Retention & Renewals"
 },
 {
  "_id": "8a87532a-7cfd-4ab7-88a9-7f14e26e842e",
  "locationId": "YTi6qs4zhiW6d4a75A9f",
  "name": "6.4 Virginia Beach Term Extension",
  "status": "draft",
  "originId": "ad0680d1-1f61-4568-b82b-a11272f31b9e",
  "permission": 380,
  "type": "workflow",
  "updatedBy": "snapshot",
  "createdAt": "2026-07-18T20:05:04.928Z",
  "updatedAt": "2026-07-18T20:05:22.616Z",
  "deleted": false,
  "dataVersion": 7,
  "parentId": "a0f037a0-e653-4f99-8e22-b5ea313be0e1",
  "permissionMeta": {
   "canRead": true,
   "canWrite": true
  },
  "id": "8a87532a-7cfd-4ab7-88a9-7f14e26e842e",
  "_folderPath": "06 - Retention & Renewals"
 },
 {
  "_id": "4da4c2d6-cc0f-4604-b0ac-d15a6a4b69e6",
  "locationId": "YTi6qs4zhiW6d4a75A9f",
  "name": "7.1 Newport News Attribution Stamp",
  "status": "draft",
  "originId": "23102f17-2601-46e1-b5dc-7e712f3e8e58",
  "permission": 380,
  "type": "workflow",
  "updatedBy": "snapshot",
  "createdAt": "2026-07-18T20:05:05.163Z",
  "updatedAt": "2026-07-18T20:05:22.526Z",
  "deleted": false,
  "dataVersion": 7,
  "parentId": "cc0d67aa-0794-4485-a24f-db1e6c669aaf",
  "permissionMeta": {
   "canRead": true,
   "canWrite": true
  },
  "id": "4da4c2d6-cc0f-4604-b0ac-d15a6a4b69e6",
  "_folderPath": "07 - System & Utilities"
 },
 {
  "_id": "755512b7-5355-45b0-88e1-8ec2e6b37f49",
  "locationId": "YTi6qs4zhiW6d4a75A9f",
  "name": "7.2 Newport News Stale Opportunity Watchdog",
  "status": "draft",
  "originId": "bc39b800-5755-49dc-894c-2c1cf9391148",
  "permission": 380,
  "type": "workflow",
  "meta": {},
  "updatedBy": "snapshot",
  "createdAt": "2026-07-18T20:05:05.749Z",
  "updatedAt": "2026-07-18T20:05:22.614Z",
  "deleted": false,
  "dataVersion": 7,
  "parentId": "cc0d67aa-0794-4485-a24f-db1e6c669aaf",
  "permissionMeta": {
   "canRead": true,
   "canWrite": true
  },
  "id": "755512b7-5355-45b0-88e1-8ec2e6b37f49",
  "_folderPath": "07 - System & Utilities"
 },
 {
  "_id": "2651f0b5-be7e-4a58-94c3-e0cd7a2ea412",
  "locationId": "YTi6qs4zhiW6d4a75A9f",
  "name": "Newport- WF-13 - Ad Platform Conversions",
  "status": "draft",
  "originId": "992da53f-1683-48cf-a496-b07e0095f8bd",
  "permission": 380,
  "type": "workflow",
  "updatedBy": "snapshot",
  "createdAt": "2026-07-18T20:05:08.843Z",
  "updatedAt": "2026-07-18T20:05:22.687Z",
  "deleted": false,
  "dataVersion": 7,
  "parentId": "cc0d67aa-0794-4485-a24f-db1e6c669aaf",
  "permissionMeta": {
   "canRead": true,
   "canWrite": true
  },
  "id": "2651f0b5-be7e-4a58-94c3-e0cd7a2ea412",
  "_folderPath": "07 - System & Utilities"
 },
 {
  "_id": "3849469f-ee08-4399-a0ff-949ea888a4d1",
  "locationId": "YTi6qs4zhiW6d4a75A9f",
  "name": "7.1 Richmond Attribution Stamp",
  "status": "draft",
  "originId": "9847e649-063b-4970-ba98-1267e48f31ea",
  "permission": 380,
  "type": "workflow",
  "updatedBy": "snapshot",
  "createdAt": "2026-07-18T20:05:05.360Z",
  "updatedAt": "2026-07-18T20:05:22.587Z",
  "deleted": false,
  "dataVersion": 7,
  "parentId": "53f1f784-f6ba-4968-9634-74eae48a78dd",
  "permissionMeta": {
   "canRead": true,
   "canWrite": true
  },
  "id": "3849469f-ee08-4399-a0ff-949ea888a4d1",
  "_folderPath": "07 - Systems & Utilities"
 },
 {
  "_id": "28e0eeaf-df23-4589-88d7-1ef4324ea0fd",
  "locationId": "YTi6qs4zhiW6d4a75A9f",
  "name": "7.1 Virginia Beach Attribution Stamp",
  "status": "draft",
  "originId": "567338b0-7c18-4362-b986-a80d3c045906",
  "permission": 380,
  "type": "workflow",
  "updatedBy": "snapshot",
  "createdAt": "2026-07-18T20:05:05.554Z",
  "updatedAt": "2026-07-18T20:05:22.552Z",
  "deleted": false,
  "dataVersion": 7,
  "parentId": "7062f134-3950-43fa-8ae9-29b165dc1c5d",
  "permissionMeta": {
   "canRead": true,
   "canWrite": true
  },
  "id": "28e0eeaf-df23-4589-88d7-1ef4324ea0fd",
  "_folderPath": "07 - Systems & Utilities"
 },
 {
  "_id": "d291f14f-c23a-4189-82b3-1e5c34bec0a8",
  "locationId": "YTi6qs4zhiW6d4a75A9f",
  "name": "7.2 Richmond Stale Opportunity Watchdog",
  "status": "draft",
  "originId": "873314a6-e8ef-4357-b6c7-0d2608520e16",
  "permission": 380,
  "type": "workflow",
  "meta": {},
  "updatedBy": "snapshot",
  "createdAt": "2026-07-18T20:05:05.939Z",
  "updatedAt": "2026-07-18T20:05:22.558Z",
  "deleted": false,
  "dataVersion": 7,
  "parentId": "53f1f784-f6ba-4968-9634-74eae48a78dd",
  "permissionMeta": {
   "canRead": true,
   "canWrite": true
  },
  "id": "d291f14f-c23a-4189-82b3-1e5c34bec0a8",
  "_folderPath": "07 - Systems & Utilities"
 },
 {
  "_id": "8daf1bd2-a58d-46e4-81a4-6234380d58bd",
  "locationId": "YTi6qs4zhiW6d4a75A9f",
  "name": "7.2 Virginia Beach Stale Opportunity Watchdog",
  "status": "draft",
  "originId": "cf4587e2-c938-4775-b13a-56dc353f58d5",
  "permission": 380,
  "type": "workflow",
  "meta": {},
  "updatedBy": "snapshot",
  "createdAt": "2026-07-18T20:05:06.247Z",
  "updatedAt": "2026-07-18T20:05:22.609Z",
  "deleted": false,
  "dataVersion": 7,
  "parentId": "7062f134-3950-43fa-8ae9-29b165dc1c5d",
  "permissionMeta": {
   "canRead": true,
   "canWrite": true
  },
  "id": "8daf1bd2-a58d-46e4-81a4-6234380d58bd",
  "_folderPath": "07 - Systems & Utilities"
 },
 {
  "_id": "b1b69cfb-e805-449d-a04a-c71eb4109c65",
  "locationId": "YTi6qs4zhiW6d4a75A9f",
  "name": "Richmond- WF-13 - Ad Platform Conversions",
  "status": "draft",
  "originId": "15a77dc5-3b31-4ddb-be9f-2ceef4fbc7c6",
  "permission": 380,
  "type": "workflow",
  "updatedBy": "snapshot",
  "createdAt": "2026-07-18T20:05:11.012Z",
  "updatedAt": "2026-07-18T20:05:23.646Z",
  "deleted": false,
  "dataVersion": 7,
  "parentId": "53f1f784-f6ba-4968-9634-74eae48a78dd",
  "permissionMeta": {
   "canRead": true,
   "canWrite": true
  },
  "id": "b1b69cfb-e805-449d-a04a-c71eb4109c65",
  "_folderPath": "07 - Systems & Utilities"
 },
 {
  "_id": "e7e42db3-58bd-435c-a810-d125614d5aaa",
  "locationId": "YTi6qs4zhiW6d4a75A9f",
  "name": "Virginia - WF-13 - Ad Platform Conversions",
  "status": "draft",
  "originId": "8c596df7-0e72-477d-b974-03f8f31fa41a",
  "permission": 380,
  "type": "workflow",
  "updatedBy": "snapshot",
  "createdAt": "2026-07-18T20:05:11.206Z",
  "updatedAt": "2026-07-18T20:05:23.659Z",
  "deleted": false,
  "dataVersion": 7,
  "parentId": "7062f134-3950-43fa-8ae9-29b165dc1c5d",
  "permissionMeta": {
   "canRead": true,
   "canWrite": true
  },
  "id": "e7e42db3-58bd-435c-a810-d125614d5aaa",
  "_folderPath": "07 - Systems & Utilities"
 },
 {
  "_id": "30ad1741-8d4f-44cc-9253-5102a21111a1",
  "locationId": "YTi6qs4zhiW6d4a75A9f",
  "name": "Bad Contact Handler",
  "status": "draft",
  "originId": "0f25f49e-0dcd-4126-9cb1-fd6854f99dc8",
  "permission": 380,
  "type": "workflow",
  "updatedBy": "snapshot",
  "createdAt": "2026-07-18T20:05:06.451Z",
  "updatedAt": "2026-07-18T20:05:22.523Z",
  "deleted": false,
  "dataVersion": 7,
  "parentId": "7c7dbaa1-3432-4326-8721-0329c10b14f1",
  "permissionMeta": {
   "canRead": true,
   "canWrite": true
  },
  "id": "30ad1741-8d4f-44cc-9253-5102a21111a1",
  "_folderPath": "Global"
 },
 {
  "_id": "3d67552e-f303-4c14-a867-5ab5b41aa048",
  "locationId": "YTi6qs4zhiW6d4a75A9f",
  "name": "First-Touch Attribution Lock",
  "status": "draft",
  "originId": "d1aabd6b-83e2-4785-b17d-dda809baa275",
  "permission": 380,
  "type": "workflow",
  "updatedBy": "snapshot",
  "createdAt": "2026-07-18T20:05:06.656Z",
  "updatedAt": "2026-07-18T20:05:22.578Z",
  "deleted": false,
  "dataVersion": 7,
  "parentId": "7c7dbaa1-3432-4326-8721-0329c10b14f1",
  "permissionMeta": {
   "canRead": true,
   "canWrite": true
  },
  "id": "3d67552e-f303-4c14-a867-5ab5b41aa048",
  "_folderPath": "Global"
 },
 {
  "_id": "20c693b4-d0d3-40af-869b-d6179ea44f84",
  "locationId": "YTi6qs4zhiW6d4a75A9f",
  "name": "Global Consent Sync",
  "status": "draft",
  "originId": "3ece0c5b-7065-4393-917e-a1bfa5bdf741",
  "permission": 380,
  "type": "workflow",
  "updatedBy": "snapshot",
  "createdAt": "2026-07-18T20:05:06.841Z",
  "updatedAt": "2026-07-18T20:05:22.596Z",
  "deleted": false,
  "dataVersion": 7,
  "parentId": "7c7dbaa1-3432-4326-8721-0329c10b14f1",
  "permissionMeta": {
   "canRead": true,
   "canWrite": true
  },
  "id": "20c693b4-d0d3-40af-869b-d6179ea44f84",
  "_folderPath": "Global"
 },
 {
  "_id": "503f6f2e-460e-4691-a15a-4d9f99e44a21",
  "locationId": "YTi6qs4zhiW6d4a75A9f",
  "name": "Global Opt-Out Handler",
  "status": "draft",
  "originId": "99cd6d41-ce9f-45e3-93b8-cd9e2a8bfebf",
  "permission": 380,
  "type": "workflow",
  "updatedBy": "snapshot",
  "createdAt": "2026-07-18T20:05:07.033Z",
  "updatedAt": "2026-07-18T20:05:22.587Z",
  "deleted": false,
  "dataVersion": 7,
  "parentId": "7c7dbaa1-3432-4326-8721-0329c10b14f1",
  "permissionMeta": {
   "canRead": true,
   "canWrite": true
  },
  "id": "503f6f2e-460e-4691-a15a-4d9f99e44a21",
  "_folderPath": "Global"
 },
 {
  "_id": "a496d271-c73d-499e-a3aa-6471ed3046fc",
  "locationId": "YTi6qs4zhiW6d4a75A9f",
  "name": "Intake Survey Completion",
  "status": "draft",
  "originId": "79a2ad54-48cd-463e-8a18-0e7eb1e92625",
  "permission": 380,
  "type": "workflow",
  "updatedBy": "snapshot",
  "createdAt": "2026-07-18T20:05:07.229Z",
  "updatedAt": "2026-07-18T20:05:22.590Z",
  "deleted": false,
  "dataVersion": 7,
  "parentId": "7c7dbaa1-3432-4326-8721-0329c10b14f1",
  "permissionMeta": {
   "canRead": true,
   "canWrite": true
  },
  "id": "a496d271-c73d-499e-a3aa-6471ed3046fc",
  "_folderPath": "Global"
 },
 {
  "_id": "1495c045-0211-450a-9923-055cc413b2cd",
  "locationId": "YTi6qs4zhiW6d4a75A9f",
  "name": "Opportunity Attribution Update",
  "status": "draft",
  "originId": "1b05a9d2-d58d-4ae7-ae90-65b9efca279f",
  "permission": 380,
  "type": "workflow",
  "updatedBy": "snapshot",
  "createdAt": "2026-07-18T20:05:09.031Z",
  "updatedAt": "2026-07-18T20:05:22.589Z",
  "deleted": false,
  "dataVersion": 7,
  "parentId": "7c7dbaa1-3432-4326-8721-0329c10b14f1",
  "permissionMeta": {
   "canRead": true,
   "canWrite": true
  },
  "id": "1495c045-0211-450a-9923-055cc413b2cd",
  "_folderPath": "Global"
 }
]